talenWF/__init__.py
talenWF/api.py
talenWF/cli.py
talenWF/utils/rvd.py
talenWF/utils/sequence.py
talenwf-0.1.2.dist-info/licenses/LICENSE
talenwf-0.1.2.dist-info/METADATA
talenwf-0.1.2.dist-info/WHEEL
talenwf-0.1.2.dist-info/entry_points.txt
talenwf-0.1.2.dist-info/top_level.txt
talenwf-0.1.2.dist-info/RECORD
